{
  "definitions": [
    {
      "title": "Hero",
      "id": "hero",
      "plugins": {
        "xwalk": {
          "page": {
            "resourceType": "core/franklin/components/block/v1/block",
            "template": {
              "name": "Hero",
              "model": "hero"
            }
          }
        }
      }
    }
  ],
  "models": [
    {
      "id": "hero",
      "fields": [
        {
          "component": "reference",
          "valueType": "string",
          "name": "image",
          "label": "Background image. Up to 5 breakpoints, mobile size first",
          "multi": false
        },
        {
          "component": "reference",
          "valueType": "string",
          "name": "image2",
          "label": "Background Image 2",
          "multi": false
        },
        {
          "component": "reference",
          "valueType": "string",
          "name": "image3",
          "label": "Background Image 3",
          "multi": false
        },
        {
          "component": "reference",
          "valueType": "string",
          "name": "image4",
          "label": "Background Image 4",
          "multi": false
        },
        {
          "component": "reference",
          "valueType": "string",
          "name": "image5",
          "label": "Background Image 5",
          "multi": false
        },
        {
          "component": "text",
          "valueType": "string",
          "name": "imageAlt",
          "label": "Alt",
          "value": ""
        },
        {
          "component": "richtext",
          "name": "text",
          "value": "",
          "label": "Text",
          "valueType": "string"
        },
        {
          "component": "select",
          "name": "classes",
          "label": "Style",
          "value": "",
          "valueType": "string",
          "description": "Teaser renders the non-homepage sub-banner layout (left-aligned overlay, teal headline).",
          "options": [
            { "name": "Default", "value": "" },
            { "name": "Teaser", "value": "teaser" }
          ]
        }
      ]
    }
  ],
  "filters": []
}
